jsw_jzyunqi/__init__.py
jsw_jzyunqi/gzip/__init__.py
jsw_jzyunqi/gzip/gz.py
jsw_jzyunqi/mbw/__init__.py
jsw_jzyunqi/mbw/publish_article.py
jsw_jzyunqi/mbw/settings.py
jsw_jzyunqi/mbw/spider_auth.py
jsw_jzyunqi-1.0.5.dist-info/METADATA
jsw_jzyunqi-1.0.5.dist-info/WHEEL
jsw_jzyunqi-1.0.5.dist-info/RECORD
